{
  "0": "Artifacts",
  "1": "Aggro",
  "2": "Control",
  "3": "Aristocrats",
  "4": "Aristocrats",
  "5": "Graveyard",
  "6": "Combo Control",
  "7": "Spellslinger",
  "8": "Counters",
  "9": "Tempo",
  "10": "Ramp",
  "11": "Stompy",
  "12": "Soup",
  "13": "Value",
  "14": "Control",
  "15": "Value",
  "16": "Midrange",
  "17": "Reanimator",
  "18": "Combo",
  "19": "Midrange",
  "20": "Blink",
  "21": "Sneak and Show",
  "22": "Midrange Combo",
  "23": "Burn",
  "24": "Tempo",
  "25": "Stompy",
  "26": "Ramp",
  "27": "Midrange",
  "28": "Aristocrats",
  "29": "Weenie",
  "30": "Value",
  "31": "Midrange",
  "32": "Midrange",
  "33": "Combo",
  "34": "Kindred",
  "35": "Midrange",
  "36": "Cycling"
}
